VerilogBM-117-133.v
/*==========================================================================================================================================================
/	
/	Title            		  :- FIFO Memory																					
/	Register No      		  :- 16CO117 - 16CO133																				
/	Abstract         		  :- FIFO Memory Implementation																		
/	Functionalities  		  :- 1. Initially, the FIFO	memory is empty and Empty signal is high.								
/		               		 	 2. When Write signal is enabled, data can be written into the memory provided it isn't full	
/								 3. If we continue entering data into the memory, data will be stored in FIFO manner.			
/								 4. Once the FIFO memory is full, Full signal will be high. If we try to write data, Overflow	
/								 	signal will be triggered.																	
/								 5. To read data from FIFO, we enable the read signal which gives out the data that was entered 
/									first.																						
/								 6. We can continue to read data from memory until it becomes empty.							
/								 7. Once the FIFO is empty, Empty signal will be high. Now, if we try to read data Underflow	
/									signal will be triggered.																		
/						  		 8. Overall, the data entered or removed follows the FIFO fashion.								
/	
/	Brief Description on code :- 	All outputs of the code are generated in the respective VCD file. This code is used to 		
/								check for several conditions like Full, Empty, Overflow, Underflow of the FIFO memory.			
/									It is important to note that read and write pointers point to the same memory location		
/								at both full and empty conditions. Therefore, in order to differentiate between the two, one	
/								extra bit is added to read and write pointers. For example if a FIFO has depth of 256 then 		
/								to span it completely 8-bits will be needed. Therefore with one extra bit read and write 		
/								pointers will be of 9-bits. When their lower 8-bits point to same memory location their MSBs 	
/								are used to ascertain whether it is a full condition or empty condition. In empty conditions 	
/								the MSBs are equal whereas in full conditionMSBs are different.									
/																															    
/	                             																								
===========================================================================================================================================================*/

// Top level Verilog code for FIFO Memory
module VerilogBM_117_133(data_out, fifo_full, fifo_empty, fifo_overflow, fifo_underflow, clk, rst_n, wr, rd, data_in);
	
	input	wr;					// Write signal
	input	rd; 				// Read signal
	input   clk; 				// Clock to drive the circuit
	input   rst_n;				// Reset signal
	input	[7:0] data_in;	 	// 8-bit input data
	
	output	[7:0] data_out;		// 8-bit output data
	output	fifo_full;			// Signal to indicate that FIFO is full
	output	fifo_empty;			// Signal to indicate that FIFO is empty
	output	fifo_overflow;		// Signal to indicate Overflow condition
	output	fifo_underflow;		// Signal to indicate Underflow condition
	
	wire	[4:0] wptr;			// Write pointer
	wire	[4:0] rptr;			// Read pointer
	wire    fifo_we;			// To indicate that data can been entered 
	wire	fifo_rd;			// To indicate that data can be read
 
	write_pointer top1(wptr, fifo_we, wr, fifo_full, clk, rst_n);
	
	read_pointer top2(rptr, fifo_rd, rd, fifo_empty, clk, rst_n);

	memory_array top3(data_out, data_in, clk, fifo_we, fifo_rd, wptr, rptr);

	status_signal top4(fifo_full, fifo_empty, fifo_overflow, fifo_underflow, wr, rd, fifo_we, fifo_rd, wptr, rptr, clk, rst_n);

endmodule

// Verilog code for Memory Array submodule
// The core of the FIFO memory
module memory_array(data_out, data_in, clk, fifo_we, fifo_rd, wptr, rptr);
	
	input	[7:0] data_in;
	input	clk,fifo_we,fifo_rd;
	input	[4:0] wptr,rptr;
	
	output	[7:0] data_out;
	
	reg		[7:0] data_out2[15:0];
	
	always @(posedge clk) begin
		
		if(fifo_we)
			data_out2[wptr[3:0]] <= data_in ;

	end
	
	assign data_out = data_out2[rptr[3:0]];

endmodule

// Verilog code for Write Pointer sub-module
// This module drives the Write pointer
module write_pointer(wptr, fifo_we, wr, fifo_full, clk, rst_n);

	input	wr, fifo_full, clk, rst_n;

	output	[4:0] wptr;
	output	fifo_we;

	reg		[4:0] wptr;
  
	assign fifo_we = (~fifo_full) & wr;
	
	always @(posedge clk or negedge rst_n) begin

		if(~rst_n)							// If reset is low, Write pointer resets
			wptr <= 5'b00000;
	
		else if(fifo_we)					// If fifo_we is high (data can be entered),
			wptr <= wptr + 5'b00001;		// write pointer increments by 1

		else								// Else, write pointer remains same
			wptr <= wptr;
	
	end

endmodule

// Verilog code for Read Pointer sub-module
// This module drives the Read pointer
module read_pointer(rptr, fifo_rd, rd, fifo_empty, clk, rst_n);

	input	rd, fifo_empty, clk, rst_n;
	
	output	[4:0] rptr;
	output	fifo_rd;
	
	reg		[4:0] rptr;
	
	assign fifo_rd = (~fifo_empty) & rd;
	
	always @(negedge clk or negedge rst_n) begin

		if(~rst_n)							// If reset is low, Read pointer resets
			rptr <= 5'b00000;
	
		else if(fifo_rd)					// If fifo_rd is high (data can be read),
			rptr <= rptr + 5'b00001;		// read pointer increments by 1

		else								// Else, read pointer remains same
			rptr <= rptr;
			
	end

endmodule

// Verilog code for Status Signals sub-module
// This module generates all the necessary output signals of FIFO memory
module status_signal(fifo_full, fifo_empty, fifo_overflow, fifo_underflow, wr, rd, fifo_we, fifo_rd, wptr, rptr, clk, rst_n);

	input	wr;
	input	rd;
	input	fifo_we;
	input	fifo_rd;
	input	clk;
	input	rst_n;
	input	[4:0] wptr;
	input	[4:0] rptr;

	output reg	fifo_full;
	output reg	fifo_empty;
	output reg	fifo_overflow;
	output reg	fifo_underflow;

	wire 	fbit_comp;						// Checks if the MSB of write and read pointers is the same
	wire	overflow_set;					// Checks overflow condition
	wire	underflow_set;					// Checks underflow condition
	wire 	pointer_equal;					// Returns high if both the read and write pointer point to the same memory location

	assign fbit_comp = wptr[4] ^ rptr[4];
	assign pointer_equal = (wptr[3:0] - rptr[3:0]) ? 0:1;
	assign overflow_set = fifo_full & wr;
	assign underflow_set = fifo_empty & rd;

	always @ * begin

		fifo_full = fbit_comp & pointer_equal;
		fifo_empty = (~fbit_comp) & pointer_equal;
	
	end

	always @(posedge clk or negedge rst_n) begin		// This snippet is used to generate Overflow signal
	
		if(~rst_n)
			fifo_overflow <= 0;

		else if((overflow_set == 1) && (fifo_rd == 0))
			fifo_overflow <= 1;
		
		else if(fifo_rd)
			fifo_overflow <= 0;

		else
			fifo_overflow <= fifo_overflow;
	
	end
 
	always @(posedge clk or negedge rst_n) begin		// This snippet is used to generate Underflow signal

		if(~rst_n)
			fifo_underflow <= 0;
		
		else if((underflow_set == 1) && (fifo_we == 0))
			fifo_underflow <= 1;

		else if(fifo_we)
			fifo_underflow <= 0;

		else
			fifo_underflow <= fifo_underflow;

	end
	
endmodule

Verilog-117-133.v
/*==========================================================================================================================================================
/	
/	Title            		  :- FIFO Memory																					
/	Register No      		  :- 16CO117 - 16CO133																				
/	Abstract         		  :- FIFO Memory Implementation																		
/	Functionalities  		  :- 1. Initially, the FIFO	memory is empty and Empty signal is high.								
/		               		 	 2. When Write signal is enabled, data can be written into the memory provided it isn't full	
/								 3. If we continue entering data into the memory, data will be stored in FIFO manner.			
/								 4. Once the FIFO memory is full, Full signal will be high. If we try to write data, Overflow	
/								 	signal will be triggered.																	
/								 5. To read data from FIFO, we enable the read signal which gives out the data that was entered 
/									first.																						
/								 6. We can continue to read data from memory until it becomes empty.							
/								 7. Once the FIFO is empty, Empty signal will be high. Now, if we try to read data Underflow	
/									signal will be triggered.																		
/						  		 8. Overall, the data entered or removed follows the FIFO fashion.								
/	
/	Brief Description on code :- 	All outputs of the code are generated in the respective VCD file. This code is used to 		
/								check for several conditions like Full, Empty, Overflow, Underflow of the FIFO memory.			
/									It is important to note that read and write pointers point to the same memory location		
/								at both full and empty conditions. Therefore, in order to differentiate between the two, one	
/								extra bit is added to read and write pointers. For example if a FIFO has depth of 256 then 		
/								to span it completely 8-bits will be needed. Therefore with one extra bit read and write 		
/								pointers will be of 9-bits. When their lower 8-bits point to same memory location their MSBs 	
/								are used to ascertain whether it is a full condition or empty condition. In empty conditions 	
/								the MSBs are equal whereas in full conditionMSBs are different.									
/																															    
/	                             																								
===========================================================================================================================================================*/

// The timescale directive  
`timescale 1 ns/ 10 ps

`define DELAY 10


module Verilog_117_133;

	// Parameter definitions
	parameter ENDTIME = 2500;	// Parameter to decide ending time of program
	
	// Input regs
	reg     clk;				// Clock to drive the circuit
	reg     rst_n;				// Reset signal (negative edge triggered)
	reg     wr;					// Write pointer
	reg     rd;					// Read pointer
	reg     [7:0] data_in;		// 8-bit input data
	
	// Output wires
	wire     [7:0] data_out;	// 8-bit output data
	wire     fifo_empty;		// Signal to indicate that FIFO is empty
	wire     fifo_full;			// Signal to indicate that FIFO is full
	wire     fifo_overflow;		// Signal to indicate Overflow condition
	wire     fifo_underflow;	// Signal to indicate Overflow condition

	integer i;					// iterator used in looping statements

	// Instantiation
	
	VerilogBM_117_133 FIFO (
	//VerilogDM_117_133 FIFO (	
		
		// Outputs
		data_out, fifo_full, fifo_empty, fifo_overflow, fifo_underflow,
		// Inputs
		clk, rst_n, wr, rd, data_in
		);
	
	// Initial Conditions
	initial begin
		   
		$dumpfile("VerilogBM-117-133.vcd");
		//$dumpfile("VerilogDM-117-133.vcd");
		$dumpvars(0, Verilog_117_133);

		clk		= 1'b0;
		rst_n	= 1'b0;
		wr		= 1'b0;
		rd		= 1'b0;
		data_in	= 8'd0;
	
	end

	// Generating Test Vectors
	initial begin
		
		   main;
	
	end
	
	task main;
	fork
		clock_generator;		// Used to generate the clock cycle
		reset_generator;		// Used to change the reset value
		operation_process;		// Driver task to write and read data in and from the FIFO memory
		result_fifo;			// Used to display the result of the code
		endsimulation;			// Task to end the simulation
	join
	endtask
	
	task clock_generator;
	begin	   
		   forever #`DELAY clk = !clk;
	end
	endtask
	
	task reset_generator;
	begin
		#(`DELAY*2)
		rst_n = 1'b1;
		# 7.9
		rst_n = 1'b0;
		# 7.09
		rst_n = 1'b1;
	end
	endtask
	
	task operation_process;
	begin
		for (i = 0; i < 17; i = i + 1) begin: WRE
			#(`DELAY*5)
			wr = 1'b1;
			data_in = data_in + 8'd1;
			#(`DELAY*2)
			wr = 1'b0;
		end
		#(`DELAY)
		for (i = 0; i < 17; i = i + 1) begin: RDE
			#(`DELAY*5)
			rd = 1'b1;
			#(`DELAY*2)
			rd = 1'b0;
		end
	end
	endtask

	// Result of fifo
	task result_fifo; 
	begin
		$display("----------------------------------------------");
		$display("----------------------------------------------");
		$display("------------- SIMULATION RESULT --------------");
		$display("----------------------------------------------");
		$display("----------------------------------------------");
		$monitor("TIME=%0d, reset=%d, wr=%b, rd=%b, data_in=%h, data_out=%h, fifo_empty=%d, fifo_full=%d, underflow=%d, overflow=%d",$time, rst_n, wr, rd, data_in, data_out, fifo_empty, fifo_full, fifo_underflow, fifo_overflow);
	end
	endtask

	// Determines the simulation limit
	task endsimulation;
	begin
		#ENDTIME
		$display("------------ THE SIMUALTION FINISHED ------------");
		$finish;
	end
	endtask

endmodule

VerilogBM-117-133.vcd
$date
	Tue Nov  7 23:13:38 2017
$end
$version
	Icarus Verilog
$end
$timescale
	10ps
$end
$scope module Verilog_117_133 $end
$var wire 8 ! data_out [7:0] $end
$var wire 1 " fifo_empty $end
$var wire 1 # fifo_full $end
$var wire 1 $ fifo_overflow $end
$var wire 1 % fifo_underflow $end
$var reg 1 & clk $end
$var reg 8 ' data_in [7:0] $end
$var integer 32 ( i [31:0] $end
$var reg 1 ) rd $end
$var reg 1 * rst_n $end
$var reg 1 + wr $end
$scope module FIFO $end
$var wire 1 , clk $end
$var wire 8 - data_in [7:0] $end
$var wire 8 . data_out [7:0] $end
$var wire 1 " fifo_empty $end
$var wire 1 # fifo_full $end
$var wire 1 $ fifo_overflow $end
$var wire 1 / fifo_rd $end
$var wire 1 % fifo_underflow $end
$var wire 1 0 fifo_we $end
$var wire 1 1 rd $end
$var wire 5 2 rptr [4:0] $end
$var wire 1 3 rst_n $end
$var wire 5 4 wptr [4:0] $end
$var wire 1 5 wr $end
$scope module top1 $end
$var wire 1 , clk $end
$var wire 1 # fifo_full $end
$var wire 1 0 fifo_we $end
$var wire 1 3 rst_n $end
$var wire 1 5 wr $end
$var reg 5 6 wptr [4:0] $end
$upscope $end
$scope module top2 $end
$var wire 1 , clk $end
$var wire 1 " fifo_empty $end
$var wire 1 / fifo_rd $end
$var wire 1 1 rd $end
$var wire 1 3 rst_n $end
$var reg 5 7 rptr [4:0] $end
$upscope $end
$scope module top3 $end
$var wire 1 , clk $end
$var wire 8 8 data_in [7:0] $end
$var wire 8 9 data_out [7:0] $end
$var wire 1 / fifo_rd $end
$var wire 1 0 fifo_we $end
$var wire 5 : rptr [4:0] $end
$var wire 5 ; wptr [4:0] $end
$upscope $end
$scope module top4 $end
$var wire 1 , clk $end
$var wire 1 < fbit_comp $end
$var wire 1 / fifo_rd $end
$var wire 1 0 fifo_we $end
$var wire 1 = overflow_set $end
$var wire 1 > pointer_equal $end
$var wire 1 1 rd $end
$var wire 5 ? rptr [4:0] $end
$var wire 1 3 rst_n $end
$var wire 1 @ underflow_set $end
$var wire 5 A wptr [4:0] $end
$var wire 1 5 wr $end
$var reg 1 B fifo_empty $end
$var reg 1 C fifo_full $end
$var reg 1 D fifo_overflow $end
$var reg 1 E fifo_underflow $end
$upscope $end
$upscope $end
$scope task clock_generator $end
$upscope $end
$scope task endsimulation $end
$upscope $end
$scope task main $end
$upscope $end
$scope task operation_process $end
$scope begin WRE $end
$upscope $end
$scope begin RDE $end
$upscope $end
$upscope $end
$scope task reset_generator $end
$upscope $end
$scope task result_fifo $end
$upscope $end
$upscope $end
$enddefinitions $end
#0
$dumpvars
0E
0D
0C
1B
b0 A
0@
b0 ?
1>
0=
0<
b0 ;
b0 :
bx 9
b0 8
b0 7
b0 6
05
b0 4
03
b0 2
01
00
0/
bx .
b0 -
0,
0+
0*
0)
b0 (
b0 '
0&
0%
0$
0#
1"
bx !
$end
#1000
1&
1,
#2000
0&
0,
1*
13
#2790
0*
03
#3000
1&
1,
#3499
1*
13
#4000
0&
0,
#5000
0B
0"
0>
b1 6
b1 4
b1 ;
b1 A
b1 !
b1 .
b1 9
10
1&
1,
b1 '
b1 -
b1 8
1+
15
#6000
0&
0,
#7000
00
1&
1,
b1 (
0+
05
#8000
0&
0,
#9000
1&
1,
#10000
0&
0,
#11000
1&
1,
#12000
10
0&
0,
b10 '
b10 -
b10 8
1+
15
#13000
b10 6
b10 4
b10 ;
b10 A
1&
1,
#14000
00
0&
0,
b10 (
0+
05
#15000
1&
1,
#16000
0&
0,
#17000
1&
1,
#18000
0&
0,
#19000
b11 6
b11 4
b11 ;
b11 A
10
1&
1,
b11 '
b11 -
b11 8
1+
15
#20000
0&
0,
#21000
00
1&
1,
b11 (
0+
05
#22000
0&
0,
#23000
1&
1,
#24000
0&
0,
#25000
1&
1,
#26000
10
0&
0,
b100 '
b100 -
b100 8
1+
15
#27000
b100 6
b100 4
b100 ;
b100 A
1&
1,
#28000
00
0&
0,
b100 (
0+
05
#29000
1&
1,
#30000
0&
0,
#31000
1&
1,
#32000
0&
0,
#33000
b101 6
b101 4
b101 ;
b101 A
10
1&
1,
b101 '
b101 -
b101 8
1+
15
#34000
0&
0,
#35000
00
1&
1,
b101 (
0+
05
#36000
0&
0,
#37000
1&
1,
#38000
0&
0,
#39000
1&
1,
#40000
10
0&
0,
b110 '
b110 -
b110 8
1+
15
#41000
b110 6
b110 4
b110 ;
b110 A
1&
1,
#42000
00
0&
0,
b110 (
0+
05
#43000
1&
1,
#44000
0&
0,
#45000
1&
1,
#46000
0&
0,
#47000
b111 6
b111 4
b111 ;
b111 A
10
1&
1,
b111 '
b111 -
b111 8
1+
15
#48000
0&
0,
#49000
00
1&
1,
b111 (
0+
05
#50000
0&
0,
#51000
1&
1,
#52000
0&
0,
#53000
1&
1,
#54000
10
0&
0,
b1000 '
b1000 -
b1000 8
1+
15
#55000
b1000 6
b1000 4
b1000 ;
b1000 A
1&
1,
#56000
00
0&
0,
b1000 (
0+
05
#57000
1&
1,
#58000
0&
0,
#59000
1&
1,
#60000
0&
0,
#61000
b1001 6
b1001 4
b1001 ;
b1001 A
10
1&
1,
b1001 '
b1001 -
b1001 8
1+
15
#62000
0&
0,
#63000
00
1&
1,
b1001 (
0+
05
#64000
0&
0,
#65000
1&
1,
#66000
0&
0,
#67000
1&
1,
#68000
10
0&
0,
b1010 '
b1010 -
b1010 8
1+
15
#69000
b1010 6
b1010 4
b1010 ;
b1010 A
1&
1,
#70000
00
0&
0,
b1010 (
0+
05
#71000
1&
1,
#72000
0&
0,
#73000
1&
1,
#74000
0&
0,
#75000
b1011 6
b1011 4
b1011 ;
b1011 A
10
1&
1,
b1011 '
b1011 -
b1011 8
1+
15
#76000
0&
0,
#77000
00
1&
1,
b1011 (
0+
05
#78000
0&
0,
#79000
1&
1,
#80000
0&
0,
#81000
1&
1,
#82000
10
0&
0,
b1100 '
b1100 -
b1100 8
1+
15
#83000
b1100 6
b1100 4
b1100 ;
b1100 A
1&
1,
#84000
00
0&
0,
b1100 (
0+
05
#85000
1&
1,
#86000
0&
0,
#87000
1&
1,
#88000
0&
0,
#89000
b1101 6
b1101 4
b1101 ;
b1101 A
10
1&
1,
b1101 '
b1101 -
b1101 8
1+
15
#90000
0&
0,
#91000
00
1&
1,
b1101 (
0+
05
#92000
0&
0,
#93000
1&
1,
#94000
0&
0,
#95000
1&
1,
#96000
10
0&
0,
b1110 '
b1110 -
b1110 8
1+
15
#97000
b1110 6
b1110 4
b1110 ;
b1110 A
1&
1,
#98000
00
0&
0,
b1110 (
0+
05
#99000
1&
1,
#100000
0&
0,
#101000
1&
1,
#102000
0&
0,
#103000
b1111 6
b1111 4
b1111 ;
b1111 A
10
1&
1,
b1111 '
b1111 -
b1111 8
1+
15
#104000
0&
0,
#105000
00
1&
1,
b1111 (
0+
05
#106000
0&
0,
#107000
1&
1,
#108000
0&
0,
#109000
1&
1,
#110000
10
0&
0,
b10000 '
b10000 -
b10000 8
1+
15
#111000
00
1=
1C
1#
1<
1>
b10000 6
b10000 4
b10000 ;
b10000 A
1&
1,
#112000
0=
0&
0,
b10000 (
0+
05
#113000
1&
1,
#114000
0&
0,
#115000
1&
1,
#116000
0&
0,
#117000
1D
1$
1=
1&
1,
b10001 '
b10001 -
b10001 8
1+
15
#118000
0&
0,
#119000
0=
1&
1,
b10001 (
0+
05
#120000
0&
0,
b0 (
#121000
1&
1,
#122000
0&
0,
#123000
1&
1,
#124000
0&
0,
#125000
0D
0$
1/
1&
1,
1)
11
#126000
0C
0#
0>
b10 !
b10 .
b10 9
b1 7
b1 2
b1 :
b1 ?
0&
0,
#127000
0/
1&
1,
b1 (
0)
01
#128000
0&
0,
#129000
1&
1,
#130000
0&
0,
#131000
1&
1,
#132000
b11 !
b11 .
b11 9
b10 7
b10 2
b10 :
b10 ?
1/
0&
0,
1)
11
#133000
1&
1,
#134000
0/
0&
0,
b10 (
0)
01
#135000
1&
1,
#136000
0&
0,
#137000
1&
1,
#138000
0&
0,
#139000
1/
1&
1,
1)
11
#140000
b100 !
b100 .
b100 9
b11 7
b11 2
b11 :
b11 ?
0&
0,
#141000
0/
1&
1,
b11 (
0)
01
#142000
0&
0,
#143000
1&
1,
#144000
0&
0,
#145000
1&
1,
#146000
b101 !
b101 .
b101 9
b100 7
b100 2
b100 :
b100 ?
1/
0&
0,
1)
11
#147000
1&
1,
#148000
0/
0&
0,
b100 (
0)
01
#149000
1&
1,
#150000
0&
0,
#151000
1&
1,
#152000
0&
0,
#153000
1/
1&
1,
1)
11
#154000
b110 !
b110 .
b110 9
b101 7
b101 2
b101 :
b101 ?
0&
0,
#155000
0/
1&
1,
b101 (
0)
01
#156000
0&
0,
#157000
1&
1,
#158000
0&
0,
#159000
1&
1,
#160000
b111 !
b111 .
b111 9
b110 7
b110 2
b110 :
b110 ?
1/
0&
0,
1)
11
#161000
1&
1,
#162000
0/
0&
0,
b110 (
0)
01
#163000
1&
1,
#164000
0&
0,
#165000
1&
1,
#166000
0&
0,
#167000
1/
1&
1,
1)
11
#168000
b1000 !
b1000 .
b1000 9
b111 7
b111 2
b111 :
b111 ?
0&
0,
#169000
0/
1&
1,
b111 (
0)
01
#170000
0&
0,
#171000
1&
1,
#172000
0&
0,
#173000
1&
1,
#174000
b1001 !
b1001 .
b1001 9
b1000 7
b1000 2
b1000 :
b1000 ?
1/
0&
0,
1)
11
#175000
1&
1,
#176000
0/
0&
0,
b1000 (
0)
01
#177000
1&
1,
#178000
0&
0,
#179000
1&
1,
#180000
0&
0,
#181000
1/
1&
1,
1)
11
#182000
b1010 !
b1010 .
b1010 9
b1001 7
b1001 2
b1001 :
b1001 ?
0&
0,
#183000
0/
1&
1,
b1001 (
0)
01
#184000
0&
0,
#185000
1&
1,
#186000
0&
0,
#187000
1&
1,
#188000
b1011 !
b1011 .
b1011 9
b1010 7
b1010 2
b1010 :
b1010 ?
1/
0&
0,
1)
11
#189000
1&
1,
#190000
0/
0&
0,
b1010 (
0)
01
#191000
1&
1,
#192000
0&
0,
#193000
1&
1,
#194000
0&
0,
#195000
1/
1&
1,
1)
11
#196000
b1100 !
b1100 .
b1100 9
b1011 7
b1011 2
b1011 :
b1011 ?
0&
0,
#197000
0/
1&
1,
b1011 (
0)
01
#198000
0&
0,
#199000
1&
1,
#200000
0&
0,
#201000
1&
1,
#202000
b1101 !
b1101 .
b1101 9
b1100 7
b1100 2
b1100 :
b1100 ?
1/
0&
0,
1)
11
#203000
1&
1,
#204000
0/
0&
0,
b1100 (
0)
01
#205000
1&
1,
#206000
0&
0,
#207000
1&
1,
#208000
0&
0,
#209000
1/
1&
1,
1)
11
#210000
b1110 !
b1110 .
b1110 9
b1101 7
b1101 2
b1101 :
b1101 ?
0&
0,
#211000
0/
1&
1,
b1101 (
0)
01
#212000
0&
0,
#213000
1&
1,
#214000
0&
0,
#215000
1&
1,
#216000
b1111 !
b1111 .
b1111 9
b1110 7
b1110 2
b1110 :
b1110 ?
1/
0&
0,
1)
11
#217000
1&
1,
#218000
0/
0&
0,
b1110 (
0)
01
#219000
1&
1,
#220000
0&
0,
#221000
1&
1,
#222000
0&
0,
#223000
1/
1&
1,
1)
11
#224000
b10000 !
b10000 .
b10000 9
b1111 7
b1111 2
b1111 :
b1111 ?
0&
0,
#225000
0/
1&
1,
b1111 (
0)
01
#226000
0&
0,
#227000
1&
1,
#228000
0&
0,
#229000
1&
1,
#230000
1@
1B
1"
0<
1>
b1 !
b1 .
b1 9
b10000 7
b10000 2
b10000 :
b10000 ?
0/
0&
0,
1)
11
#231000
1E
1%
1&
1,
#232000
0@
0&
0,
b10000 (
0)
01
#233000
1&
1,
#234000
0&
0,
#235000
1&
1,
#236000
0&
0,
#237000
1@
1&
1,
1)
11
#238000
0&
0,
#239000
0@
1&
1,
b10001 (
0)
01
